earl_sdk/__init__.py
earl_sdk/_version.py
earl_sdk/api.py
earl_sdk/auth.py
earl_sdk/client.py
earl_sdk/exceptions.py
earl_sdk/models.py
earl_sdk-0.3.4.dist-info/METADATA
earl_sdk-0.3.4.dist-info/WHEEL
earl_sdk-0.3.4.dist-info/RECORD
