Metadata-Version: 2.4
Name: earl-sdk
Version: 0.3.4
Summary: Python SDK for Earl Medical Evaluation Platform
Project-URL: Homepage, https://thelumos.ai
Project-URL: Documentation, https://docs.thelumos.ai/sdk/python
Project-URL: Repository, https://github.com/TheLumos/earl-sdk-python
Project-URL: Issues, https://github.com/TheLumos/earl-sdk-python/issues
Author-email: TheLumos <dmitriy@thelumos.ai>
License-Expression: MIT
Keywords: ai,earl,evaluation,healthcare,medical,reinforcement learning,sdk
Classifier: Development Status :: 4 - Beta
Classifier: Intended Audience :: Developers
Classifier: License :: OSI Approved :: MIT License
Classifier: Operating System :: OS Independent
Classifier: Programming Language :: Python :: 3
Classifier: Programming Language :: Python :: 3.10
Classifier: Programming Language :: Python :: 3.11
Classifier: Programming Language :: Python :: 3.12
Classifier: Programming Language :: Python :: 3.13
Classifier: Topic :: Scientific/Engineering :: Artificial Intelligence
Classifier: Topic :: Scientific/Engineering :: Medical Science Apps.
Classifier: Typing :: Typed
Requires-Python: >=3.10
Provides-Extra: dev
Requires-Dist: black>=24.0; extra == 'dev'
Requires-Dist: mypy>=1.8; extra == 'dev'
Requires-Dist: pytest-asyncio>=0.23; extra == 'dev'
Requires-Dist: pytest>=8.0; extra == 'dev'
Requires-Dist: ruff>=0.1; extra == 'dev'
